ssp_controller/ssp_controller.srcs/sources_1/new/tx_rx_logic.v
`timescale 1ns / 1ps
//////////////////////////////////////////////////////////////////////////////////
// Company: 
// Engineer: 
// 
// Create Date: 11/13/2025 09:43:55 PM
// Design Name: 
// Module Name: tx_rx_logic
// Project Name: 
// Target Devices: 
// Tool Versions: 
// Description: 
// 
// Dependencies: 
// 
// Revision:
// Revision 0.01 - File Created
// Additional Comments:
// 
//////////////////////////////////////////////////////////////////////////////////


module tx_rx_logic(
        input CLEAR_B,
        input PCLK,
        input SSPCLKOUT,
        output reg SSPOE_B,
        
        //Tx
        input [7:0] TxData,//Tx parallel data in
        input tx_empty,
        input tx_full, //unused (should be used by processor)
        output reg SSPTXD,
        output reg SSPFSSOUT,
        output reg tx_read,
        
        //Rx
        input SSPFSSIN,
        input SSPRXD, //Rx serial data in
        input rx_empty,//unused (should be used by processor)
        input rx_full,
        output reg rx_write
    );
    
    //tx
    localparam tx_IDLE = 2'b00;
    localparam tx_LOAD = 2'b01;
    localparam tx_SHIFT = 2'b10;
    reg [1:0] tx_state;
    reg [7:0] shift_reg;
    reg[3:0] bit_count_tx;
    
    //rx
    reg [3:0] bit_count_rx;
    localparam rx_IDLE = 2'b00;
    localparam rx_WAIT = 2'b01;
    localparam rx_SHIFT = 2'b10;
    reg [1:0] rx_state;
    reg [7:0] parallel_reg;
    
    wire CLEAR = ~CLEAR_B;
    
    always@(negedge SSPCLKOUT) begin
        if ((tx_state == tx_LOAD || tx_state == tx_SHIFT) && SSPFSSIN == 1)begin
            SSPOE_B <= 1'b0;
        end
        else if (tx_state == tx_IDLE) begin 
            SSPOE_B <= 1'b1;
        end
    end
    
    //tx logic
    always@(posedge SSPCLKOUT) begin
        case (tx_state)
            tx_IDLE: begin
                SSPTXD <= 0;
                SSPFSSOUT <= 0;
                bit_count_tx <= 0;
                tx_read <= 0;     
                shift_reg <= 8'd0;      
                if (tx_empty == 0) begin //otherwise stay at IDLE state if tx_emtpy = 1
                    tx_state <= tx_LOAD;
                end
            end
            tx_LOAD: begin
                shift_reg <= TxData;
                SSPFSSOUT <= 1; //high for bit before msb
                bit_count_tx <= 0;
                tx_state <= tx_SHIFT;
                if (tx_empty == 0) begin
                    tx_read <= 1; //read next data from fifo if next data is available
                end
            end
            tx_SHIFT: begin
                tx_read <= 0;
                SSPFSSOUT <= 0; //low for all bits
                SSPTXD <= shift_reg[7]; //send 1 bit serially 
                shift_reg <= {shift_reg[6:0],1'b0};
                bit_count_tx <= bit_count_tx + 1;
                
                if (bit_count_tx == 7) begin
                    //tx_read <= 1; //read from fifo to remove item
                    bit_count_tx <= 0;
                    if (tx_read == 1 && tx_empty == 0) begin //more data to transmit
                        tx_read <= 0;
                        tx_state <= tx_SHIFT;
                        shift_reg <= TxData;
                        SSPFSSOUT <= 1; //high for lsb if there is a next data
                    end
                    else begin
                        tx_state <= tx_LOAD;
                    end
                    
                    if (tx_empty == 1) begin
                        tx_state <= tx_IDLE;
                    end
                    else if (tx_empty == 0) begin
                        tx_read <= 1;
                    end
                end
            end
            default: begin
                tx_state <= tx_IDLE; 
            end
        endcase
    end
    
    //rx logic
    always@(posedge SSPCLKOUT) begin 
        case (rx_state)
            rx_IDLE: begin
                bit_count_rx <= 4'd8;   
                parallel_reg <= 8'd0;  
                rx_write <= 1'b0;      
                if (rx_full == 0) begin //otherwise stay at IDLE state if rx_full = 1
                    rx_state <= rx_WAIT;
                end
            end
            rx_WAIT: begin
                if (SSPFSSIN == 1) begin
                    bit_count_rx <= 4'd7;
                    rx_state <= rx_SHIFT;
                end
            end
            rx_SHIFT: begin
                bit_count_rx <= bit_count_rx - 1;
                parallel_reg <= {SSPRXD, parallel_reg[7:1]}; //save 1 serial bit
                if (bit_count_rx == 0) begin //done collecting all bits
                    rx_write <= 1; //write incoming parallel register to fifo
                    if (rx_full == 0) begin //more data to transmit
                        rx_state <= rx_WAIT;
                    end
                    else if (rx_full == 1) begin //no more data to transmit
                        rx_state <= rx_IDLE;
                    end
                end
            end
            default: begin
                rx_state <= rx_IDLE;
            end
        endcase
    end
endmodule

ssp_controller/ssp_controller.srcs/sim_1/new/tb3_tx_rx_logic.v
`timescale 1ns / 1ps

// This is pure Verilog-2001 compatible with Vivado XSim
module tb_tx_rx_logic;

    // DUT ports
    reg         CLEAR_B;
    reg         PCLK;
    reg         SSPCLKOUT;
   
    reg  [7:0] TxData;
    reg         tx_empty;
    reg         tx_full;
    reg         rx_empty;
    reg         rx_full;
   
    reg         SSPFSSIN;
    reg         SSPRXD;
    wire        SSPOE_B;
    wire        SSPTXD;
    wire        SSPFSSOUT;
    wire        tx_read;
    wire        rx_write;

    // Loopback connections
    always @(SSPTXD)    SSPRXD    = SSPTXD;
    always @(SSPFSSOUT) SSPFSSIN = SSPFSSOUT;

    // Clock generation
    always #50 SSPCLKOUT = ~SSPCLKOUT; // 10 MHz (100ns period)
    always #20 PCLK = ~PCLK;           // 25 MHz

    // === Explicit port mapping required in Verilog ===
    tx_rx_logic dut (
        .CLEAR_B     (CLEAR_B),
        .PCLK        (PCLK),
        .SSPCLKOUT   (SSPCLKOUT),
        .TxData      (TxData),
        .tx_empty    (tx_empty),
        .tx_full     (tx_full),
        .rx_empty    (rx_empty),
        .rx_full     (rx_full),
        .SSPFSSIN    (SSPFSSIN),
        .SSPRXD      (SSPRXD),
        .SSPOE_B     (SSPOE_B),
        .SSPTXD      (SSPTXD),
        .SSPFSSOUT   (SSPFSSOUT),
        .tx_read     (tx_read),
        .rx_write    (rx_write)
    );

    // Initial values
    initial begin
        CLEAR_B   = 0;
        PCLK      = 0;
        SSPCLKOUT = 0;
        TxData    = 8'h00;
        tx_empty  = 1;
        tx_full   = 0;
        rx_empty  = 1;
        rx_full   = 0;
        SSPFSSIN  = 0;
        SSPRXD    = 0;

        $display("=== Clean Back-to-Back SSP Testbench ===");
        $dumpfile("tb_tx_rx_logic.vcd");
        $dumpvars(0, tb_tx_rx_logic);

        // Reset pulse
        #300;
        CLEAR_B = 1;
        #300;

        // Start transmission: FIFO no longer empty
        @(posedge SSPCLKOUT);
        tx_empty = 0;  // stays 0 until we finish sending

        // Send 4 bytes back-to-back
        TxData = 8'h55; #500;
        TxData = 8'hAA; #500;
        TxData = 8'hC3; #800;
        TxData = 8'h3C; #500;

        // Declare FIFO empty again → transmission stops
        tx_empty = 1;

        // Wait for all 4 bytes to be received (rx_write pulses)
        repeat(4) @(posedge rx_write);

        #2000;
        $display("=== ALL 4 BYTES RECEIVED CORRECTLY ===");
        $display("Simulation finished successfully!");
        $finish;
    end

    // Nice console monitor
    initial begin
        $monitor("%0tps | FSS=%b TXD=%b OE_B=%b | tx_state=%0d bit_cnt=%0d tx_read=%b rx_write=%b",
                 $time, SSPFSSOUT, SSPTXD, SSPOE_B,
                 dut.tx_state, dut.bit_count_tx, tx_read, rx_write);
    end

endmodule

ssp_controller/ssp_controller.sim/sim_1/behav/xsim/tb_tx_rx_logic.vcd
$date
   Tue Nov 25 19:37:32 2025
$end

$version
  2024.2.0
  $dumpfile ("tb_tx_rx_logic.vcd") 
$end

$timescale
  1ps
$end

$scope module tb_tx_rx_logic $end
$var reg 1 ! CLEAR_B $end
$var reg 1 " PCLK $end
$var reg 1 # SSPCLKOUT $end
$var reg 8 $ TxData [7:0] $end
$var reg 1 % tx_empty $end
$var reg 1 & tx_full $end
$var reg 1 ' rx_empty $end
$var reg 1 ( rx_full $end
$var reg 1 ) SSPFSSIN $end
$var reg 1 * SSPRXD $end
$var wire 1 + SSPOE_B $end
$var wire 1 , SSPTXD $end
$var wire 1 - SSPFSSOUT $end
$var wire 1 . tx_read $end
$var wire 1 / rx_write $end
$scope module dut $end
$var wire 1 0 CLEAR_B $end
$var wire 1 1 PCLK $end
$var wire 1 2 SSPCLKOUT $end
$var reg 1 3 SSPOE_B $end
$var wire 8 4 TxData [7:0] $end
$var wire 1 5 tx_empty $end
$var wire 1 6 tx_full $end
$var reg 1 7 SSPTXD $end
$var reg 1 8 SSPFSSOUT $end
$var reg 1 9 tx_read $end
$var wire 1 : SSPFSSIN $end
$var wire 1 ; SSPRXD $end
$var wire 1 < rx_empty $end
$var wire 1 = rx_full $end
$var reg 1 > rx_write $end
$var reg 2 ? tx_state [1:0] $end
$var reg 8 @ shift_reg [7:0] $end
$var reg 4 A bit_count_tx [3:0] $end
$var reg 4 B bit_count_rx [3:0] $end
$var reg 2 C rx_state [1:0] $end
$var reg 8 D parallel_reg [7:0] $end
$var wire 1 E CLEAR $end
$upscope $end
$upscope $end
$enddefinitions $end

#0
$dumpvars
0!
0"
0#
b0 $
1%
0&
1'
0(
0)
0*
x+
x,
x-
x.
x/
00
01
02
x3
b0 4
15
06
x7
x8
x9
0:
0;
1<
0=
x>
bx ?
bx @
bx A
bx B
bx C
bx D
1E
$end

#20000
1"
11

#40000
0"
01

#50000
1#
12
b0 ?
b0 C

#60000
1"
11

#80000
0"
01

#100000
1"
0#
1+
11
02
13

#120000
0"
01

#140000
1"
11

#150000
1#
0,
0-
0.
0/
12
07
08
09
0>
b0 @
b0 A
b1000 B
b1 C
b0 D

#160000
0"
01

#180000
1"
11

#200000
0"
0#
01
02

#220000
1"
11

#240000
0"
01

#250000
1#
12

#260000
1"
11

#280000
0"
01

#300000
1!
1"
0#
10
11
02
0E

#320000
0"
01

#340000
1"
11

#350000
1#
12

#360000
0"
01

#380000
1"
11

#400000
0"
0#
01
02

#420000
1"
11

#440000
0"
01

#450000
1#
12

#460000
1"
11

#480000
0"
01

#500000
1"
0#
11
02

#520000
0"
01

#540000
1"
11

#550000
1#
12

#560000
0"
01

#580000
1"
11

#600000
0"
0#
01
02

#620000
1"
11

#640000
0"
01

#650000
1#
b1010101 $
0%
12
b1010101 4
05
b1 ?

#660000
1"
11

#680000
0"
01

#700000
1"
0#
11
02

#720000
0"
01

#740000
1"
11

#750000
1#
1)
1-
1.
12
18
19
1:
b10 ?
b1010101 @

#760000
0"
01

#780000
1"
11

#800000
0"
0#
0+
01
02
03

#820000
1"
11

#840000
0"
01

#850000
1#
0)
0-
12
08
0:
b10101010 @
b1 A
b111 B
b10 C

#860000
1"
11

#880000
0"
01

#900000
1"
0#
11
02

#920000
0"
01

#940000
1"
11

#950000
1#
1*
1,
12
17
1;
b1010100 @
b10 A
b110 B

#960000
0"
01

#980000
1"
11

#1000000
0"
0#
01
02

#1020000
1"
11

#1040000
0"
01

#1050000
1#
0*
0,
12
07
0;
b10101000 @
b11 A
b101 B
b10000000 D

#1060000
1"
11

#1080000
0"
01

#1100000
1"
0#
11
02

#1120000
0"
01

#1140000
1"
11

#1150000
1#
b10101010 $
1*
1,
12
b10101010 4
17
1;
b1010000 @
b100 A
b100 B
b1000000 D

#1160000
0"
01

#1180000
1"
11

#1200000
0"
0#
01
02

#1220000
1"
11

#1240000
0"
01

#1250000
1#
0*
0,
12
07
0;
b10100000 @
b101 A
b11 B
b10100000 D

#1260000
1"
11

#1280000
0"
01

#1300000
1"
0#
11
02

#1320000
0"
01

#1340000
1"
11

#1350000
1#
1*
1,
12
17
1;
b1000000 @
b110 A
b10 B
b1010000 D

#1360000
0"
01

#1380000
1"
11

#1400000
0"
0#
01
02

#1420000
1"
11

#1440000
0"
01

#1450000
1#
0*
0,
12
07
0;
b10000000 @
b111 A
b1 B
b10101000 D

#1460000
1"
11

#1480000
0"
01

#1500000
1"
0#
11
02

#1520000
0"
01

#1540000
1"
11

#1550000
1#
1)
1*
1,
1-
12
17
18
1:
1;
b1 ?
b10101010 @
b0 A
b0 B
b1010100 D

#1560000
0"
01

#1580000
1"
11

#1600000
0"
0#
01
02

#1620000
1"
11

#1640000
0"
01

#1650000
1#
b11000011 $
1/
12
b11000011 4
1>
b10 ?
b11000011 @
b1111 B
b1 C
b10101010 D

#1660000
1"
11

#1680000
0"
01

#1700000
1"
0#
11
02

#1720000
0"
01

#1740000
1"
11

#1750000
1#
0)
0-
12
08
0:
b10000110 @
b1 A
b111 B
b10 C

#1760000
0"
01

#1780000
1"
11

#1800000
0"
0#
01
02

#1820000
1"
11

#1840000
0"
01

#1850000
1#
12
b1100 @
b10 A
b110 B
b11010101 D

#1860000
1"
11

#1880000
0"
01

#1900000
1"
0#
11
02

#1920000
0"
01

#1940000
1"
11

#1950000
1#
0*
0,
12
07
0;
b11000 @
b11 A
b101 B
b11101010 D

#1960000
0"
01

#1980000
1"
11

#2000000
0"
0#
01
02

#2020000
1"
11

#2040000
0"
01

#2050000
1#
12
b110000 @
b100 A
b100 B
b1110101 D

#2060000
1"
11

#2080000
0"
01

#2100000
1"
0#
11
02

#2120000
0"
01

#2140000
1"
11

#2150000
1#
12
b1100000 @
b101 A
b11 B
b111010 D

#2160000
0"
01

#2180000
1"
11

#2200000
0"
0#
01
02

#2220000
1"
11

#2240000
0"
01

#2250000
1#
12
b11000000 @
b110 A
b10 B
b11101 D

#2260000
1"
11

#2280000
0"
01

#2300000
1"
0#
11
02

#2320000
0"
01

#2340000
1"
11

#2350000
1#
1*
1,
12
17
1;
b10000000 @
b111 A
b1 B
b1110 D

#2360000
0"
01

#2380000
1"
11

#2400000
0"
0#
01
02

#2420000
1"
11

#2440000
0"
01

#2450000
1#
b111100 $
1)
1-
12
b111100 4
18
1:
b1 ?
b111100 @
b0 A
b0 B
b10000111 D

#2460000
1"
11

#2480000
0"
01

#2500000
1"
0#
11
02

#2520000
0"
01

#2540000
1"
11

#2550000
1#
12
b10 ?
b1111 B
b1 C
b11000011 D

#2560000
0"
01

#2580000
1"
11

#2600000
0"
0#
01
02

#2620000
1"
11

#2640000
0"
01

#2650000
1#
0)
0*
0,
0-
12
07
08
0:
0;
b1111000 @
b1 A
b111 B
b10 C

#2660000
1"
11

#2680000
0"
01

#2700000
1"
0#
11
02

#2720000
0"
01

#2740000
1"
11

#2750000
1#
12
b11110000 @
b10 A
b110 B
b1100001 D

#2760000
0"
01

#2780000
1"
11

#2800000
0"
0#
01
02

#2820000
1"
11

#2840000
0"
01

#2850000
1#
1*
1,
12
17
1;
b11100000 @
b11 A
b101 B
b110000 D

#2860000
1"
11

#2880000
0"
01

#2900000
1"
0#
11
02

#2920000
0"
01

#2940000
1"
11

#2950000
1#
1%
12
15
b11000000 @
b100 A
b100 B
b10011000 D

#2960000
0"
01

#2980000
1"
11

#3000000
0"
0#
01
02

#3020000
1"
11

#3040000
0"
01

#3050000
1#
12
b10000000 @
b101 A
b11 B
b11001100 D

#3060000
1"
11

#3080000
0"
01

#3100000
1"
0#
11
02

#3120000
0"
01

#3140000
1"
11

#3150000
1#
12
b0 @
b110 A
b10 B
b11100110 D

#3160000
0"
01

#3180000
1"
11

#3200000
0"
0#
01
02

#3220000
1"
11

#3240000
0"
01

#3250000
1#
0*
0,
12
07
0;
b111 A
b1 B
b11110011 D

#3260000
1"
11

#3280000
0"
01

#3300000
1"
0#
11
02

#3320000
0"
01

#3340000
1"
11

#3350000
1#
12
b0 ?
b0 A
b0 B
b1111001 D

#3360000
0"
01

#3380000
1"
11

#3400000
0"
0#
1+
01
02
13

#3420000
1"
11

#3440000
0"
01

#3450000
1#
0.
12
09
b1111 B
b1 C
b111100 D

#3460000
1"
11

#3480000
0"
01

#3500000
1"
0#
11
02

#3520000
0"
01

#3540000
1"
11

#3550000
1#
12

#3560000
0"
01

#3580000
1"
11

#3600000
0"
0#
01
02

#3620000
1"
11

#3640000
0"
01

#3650000
1#
12

#3660000
1"
11

#3680000
0"
01

#3700000
1"
0#
11
02

#3720000
0"
01

#3740000
1"
11

#3750000
1#
12

#3760000
0"
01

#3780000
1"
11

#3800000
0"
0#
01
02

#3820000
1"
11

#3840000
0"
01

#3850000
1#
12

#3860000
1"
11

#3880000
0"
01

#3900000
1"
0#
11
02

#3920000
0"
01

#3940000
1"
11

#3950000
1#
12

#3960000
0"
01

#3980000
1"
11

#4000000
0"
0#
01
02

#4020000
1"
11

#4040000
0"
01

#4050000
1#
12

#4060000
1"
11

#4080000
0"
01

#4100000
1"
0#
11
02

#4120000
0"
01

#4140000
1"
11

#4150000
1#
12

#4160000
0"
01

#4180000
1"
11

#4200000
0"
0#
01
02

#4220000
1"
11

#4240000
0"
01

#4250000
1#
12

#4260000
1"
11

#4280000
0"
01

#4300000
1"
0#
11
02

#4320000
0"
01

#4340000
1"
11

#4350000
1#
12

#4360000
0"
01

#4380000
1"
11

#4400000
0"
0#
01
02

#4420000
1"
11

#4440000
0"
01

#4450000
1#
12

#4460000
1"
11

#4480000
0"
01

#4500000
1"
0#
11
02

#4520000
0"
01

#4540000
1"
11

#4550000
1#
12

#4560000
0"
01

#4580000
1"
11

#4600000
0"
0#
01
02

#4620000
1"
11

#4640000
0"
01

#4650000
1#
12

#4660000
1"
11

#4680000
0"
01

#4700000
1"
0#
11
02

#4720000
0"
01

#4740000
1"
11

#4750000
1#
12

#4760000
0"
01

#4780000
1"
11

#4800000
0"
0#
01
02

#4820000
1"
11

#4840000
0"
01

#4850000
1#
12

#4860000
1"
11

#4880000
0"
01

#4900000
1"
0#
11
02

#4920000
0"
01

#4940000
1"
11

#4950000
1#
12

#4960000
0"
01

#4980000
1"
11

#5000000
0"
0#
01
02

#5020000
1"
11

#5040000
0"
01

#5050000
1#
12

#5060000
1"
11

#5080000
0"
01

#5100000
1"
0#
11
02

#5120000
0"
01

#5140000
1"
11

#5150000
1#
12

#5160000
0"
01

#5180000
1"
11

#5200000
0"
0#
01
02

#5220000
1"
11

#5240000
0"
01

#5250000
1#
12

#5260000
1"
11

#5280000
0"
01

#5300000
1"
0#
11
02

#5320000
0"
01

#5340000
1"
11

#5350000
1#
12

#5360000
0"
01

#5380000
1"
11

#5400000
0"
0#
01
02

#5420000
1"
11

#5440000
0"
01

#5450000
1#
12

#5460000
1"
11

#5480000
0"
01

#5500000
1"
0#
11
02

#5520000
0"
01

#5540000
1"
11

#5550000
1#
12

#5560000
0"
01

#5580000
1"
11

#5600000
0"
0#
01
02

#5620000
1"
11

#5640000
0"
01

#5650000
1#
12

#5660000
1"
11

#5680000
0"
01

#5700000
1"
0#
11
02

#5720000
0"
01

#5740000
1"
11

#5750000
1#
12

#5760000
0"
01

#5780000
1"
11

#5800000
0"
0#
01
02

#5820000
1"
11

#5840000
0"
01

#5850000
1#
12

#5860000
1"
11

#5880000
0"
01

#5900000
1"
0#
11
02

#5920000
0"
01

#5940000
1"
11

#5950000
1#
12

#5960000
0"
01

#5980000
1"
11

#6000000
0"
0#
01
02

#6020000
1"
11

#6040000
0"
01

#6050000
1#
12

#6060000
1"
11

#6080000
0"
01

#6100000
1"
0#
11
02

#6120000
0"
01

#6140000
1"
11

#6150000
1#
12

#6160000
0"
01

#6180000
1"
11

#6200000
0"
0#
01
02

#6220000
1"
11

#6240000
0"
01

#6250000
1#
12

#6260000
1"
11

#6280000
0"
01

#6300000
1"
0#
11
02

#6320000
0"
01

#6340000
1"
11

#6350000
1#
12

#6360000
0"
01

#6380000
1"
11

#6400000
0"
0#
01
02

#6420000
1"
11

#6440000
0"
01

#6450000
1#
12

#6460000
1"
11

#6480000
0"
01

#6500000
1"
0#
11
02

#6520000
0"
01

#6540000
1"
11

#6550000
1#
12

#6560000
0"
01

#6580000
1"
11

#6600000
0"
0#
01
02

#6620000
1"
11

#6640000
0"
01

#6650000
1#
12

#6660000
1"
11

#6680000
0"
01

#6700000
1"
0#
11
02

#6720000
0"
01

#6740000
1"
11

#6750000
1#
12

#6760000
0"
01

#6780000
1"
11

#6800000
0"
0#
01
02

#6820000
1"
11

#6840000
0"
01

#6850000
1#
12

#6860000
1"
11

#6880000
0"
01

#6900000
1"
0#
11
02

#6920000
0"
01

#6940000
1"
11

#6950000
1#
12

#6960000
0"
01

#6980000
1"
11

#7000000
0"
0#
01
02

#7020000
1"
11

#7040000
0"
01

#7050000
1#
12

#7060000
1"
11

#7080000
0"
01

#7100000
1"
0#
11
02

#7120000
0"
01

#7140000
1"
11

#7150000
1#
12

#7160000
0"
01

#7180000
1"
11

#7200000
0"
0#
01
02

#7220000
1"
11

#7240000
0"
01

#7250000
1#
12

#7260000
1"
11

#7280000
0"
01

#7300000
1"
0#
11
02

#7320000
0"
01

#7340000
1"
11

#7350000
1#
12

#7360000
0"
01

#7380000
1"
11

#7400000
0"
0#
01
02

#7420000
1"
11

#7440000
0"
01

#7450000
1#
12

#7460000
1"
11

#7480000
0"
01

#7500000
1"
0#
11
02

#7520000
0"
01

#7540000
1"
11

#7550000
1#
12

#7560000
0"
01

#7580000
1"
11

#7600000
0"
0#
01
02

#7620000
1"
11

#7640000
0"
01

#7650000
1#
12

#7660000
1"
11

#7680000
0"
01

#7700000
1"
0#
11
02

#7720000
0"
01

#7740000
1"
11

#7750000
1#
12

#7760000
0"
01

#7780000
1"
11

#7800000
0"
0#
01
02

#7820000
1"
11

#7840000
0"
01

#7850000
1#
12

#7860000
1"
11

#7880000
0"
01

#7900000
1"
0#
11
02

#7920000
0"
01

#7940000
1"
11

#7950000
1#
12

#7960000
0"
01

#7980000
1"
11

#8000000
0"
0#
01
02

#8020000
1"
11

#8040000
0"
01

#8050000
1#
12

#8060000
1"
11

#8080000
0"
01

#8100000
1"
0#
11
02

#8120000
0"
01

#8140000
1"
11

#8150000
1#
12

#8160000
0"
01

#8180000
1"
11

#8200000
0"
0#
01
02

#8220000
1"
11

#8240000
0"
01

#8250000
1#
12

#8260000
1"
11

#8280000
0"
01

#8300000
1"
0#
11
02

#8320000
0"
01

#8340000
1"
11

#8350000
1#
12

#8360000
0"
01

#8380000
1"
11

#8400000
0"
0#
01
02

#8420000
1"
11

#8440000
0"
01

#8450000
1#
12

#8460000
1"
11

#8480000
0"
01

#8500000
1"
0#
11
02

#8520000
0"
01

#8540000
1"
11

#8550000
1#
12

#8560000
0"
01

#8580000
1"
11

#8600000
0"
0#
01
02

#8620000
1"
11

#8640000
0"
01

#8650000
1#
12

#8660000
1"
11

#8680000
0"
01

#8700000
1"
0#
11
02

#8720000
0"
01

#8740000
1"
11

#8750000
1#
12

#8760000
0"
01

#8780000
1"
11

#8800000
0"
0#
01
02

#8820000
1"
11

#8840000
0"
01

#8850000
1#
12

#8860000
1"
11

#8880000
0"
01

#8900000
1"
0#
11
02

#8920000
0"
01

#8940000
1"
11

#8950000
1#
12

#8960000
0"
01

#8980000
1"
11

#9000000
0"
0#
01
02

#9020000
1"
11

#9040000
0"
01

#9050000
1#
12

#9060000
1"
11

#9080000
0"
01

#9100000
1"
0#
11
02

#9120000
0"
01

#9140000
1"
11

#9150000
1#
12

#9160000
0"
01

#9180000
1"
11

#9200000
0"
0#
01
02

#9220000
1"
11

#9240000
0"
01

#9250000
1#
12

#9260000
1"
11

#9280000
0"
01

#9300000
1"
0#
11
02

#9320000
0"
01

#9340000
1"
11

#9350000
1#
12

#9360000
0"
01

#9380000
1"
11

#9400000
0"
0#
01
02

#9420000
1"
11

#9440000
0"
01

#9450000
1#
12

#9460000
1"
11

#9480000
0"
01

#9500000
1"
0#
11
02

#9520000
0"
01

#9540000
1"
11

#9550000
1#
12

#9560000
0"
01

#9580000
1"
11

#9600000
0"
0#
01
02

#9620000
1"
11

#9640000
0"
01

#9650000
1#
12

#9660000
1"
11

#9680000
0"
01

#9700000
1"
0#
11
02

#9720000
0"
01

#9740000
1"
11

#9750000
1#
12

#9760000
0"
01

#9780000
1"
11

#9800000
0"
0#
01
02

#9820000
1"
11

#9840000
0"
01

#9850000
1#
12

#9860000
1"
11

#9880000
0"
01

#9900000
1"
0#
11
02

#9920000
0"
01

#9940000
1"
11

#9950000
1#
12

#9960000
0"
01

#9980000
1"
11

#10000000
0"
0#
01
02
